arqsim/__init__.py
arqsim/core.py
arqsim-0.1.dist-info/licenses/LICENSE
arqsim-0.1.dist-info/METADATA
arqsim-0.1.dist-info/WHEEL
arqsim-0.1.dist-info/entry_points.txt
arqsim-0.1.dist-info/top_level.txt
arqsim-0.1.dist-info/RECORD
