Metadata-Version: 2.4
Name: arqsim
Version: 0.1
Summary: Simulate ARQ protocols: Stop-and-Wait, Go-Back-N, Selective Repeat
Author: Your Name
Author-email: you@example.com
Classifier: Programming Language :: Python :: 3
Classifier: License :: OSI Approved :: MIT License
Requires-Python: >=3.6
License-File: LICENSE
Dynamic: author
Dynamic: author-email
Dynamic: classifier
Dynamic: license-file
Dynamic: requires-python
Dynamic: summary
